{
  "PageId": 255923,
  "PageTitle": "Challenge",
  "PageUrl": "https://starwars.fandom.com/wiki/Challenge",
  "Titles": {
    "Values": [
      "Challenge"
    ],
    "Links": []
  },
  "Author(s)": {
    "Values": [
      "Margaret van Poelgeest-Heintz"
    ],
    "Links": [
      {
        "Content": "Margaret van Poelgeest-Heintz",
        "Href": "/wiki/Margaret_van_Poelgeest-Heintz"
      }
    ]
  },
  "Publisher": {
    "Values": [
      "Wizards of the Coast"
    ],
    "Links": [
      {
        "Content": "Wizards of the Coast",
        "Href": "/wiki/Wizards_of_the_Coast"
      }
    ]
  },
  "Game": {
    "Values": [
      "Star Wars Roleplaying Game"
    ],
    "Links": [
      {
        "Content": "Star Wars Roleplaying Game",
        "Href": "/wiki/Star_Wars_Roleplaying_Game"
      }
    ]
  },
  "Release date": {
    "Values": [
      "2005"
    ],
    "Links": [
      {
        "Content": "2005",
        "Href": "/wiki/2005"
      }
    ]
  },
  "Pages": {
    "Values": [
      "19"
    ],
    "Links": []
  },
  "Timeline": {
    "Values": [
      "20 BBY"
    ],
    "Links": [
      {
        "Content": "20 BBY",
        "Href": "/wiki/20_BBY/Legends"
      }
    ]
  },
  "Campaign": {
    "Values": [
      "Living Force campaign"
    ],
    "Links": [
      {
        "Content": "Living Force campaign",
        "Href": "/wiki/Living_Force_(roleplaying_campaign)"
      }
    ]
  },
  "Preceded by": {
    "Values": [
      "Decision: Cularin"
    ],
    "Links": [
      {
        "Content": "Decision: Cularin",
        "Href": "/wiki/Decision:_Cularin"
      }
    ]
  },
  "Followed by": {
    "Values": [
      "Revelations"
    ],
    "Links": [
      {
        "Content": "Revelations",
        "Href": "/wiki/Revelations"
      }
    ]
  },
  "Template": {
    "Values": [
      "[Source]"
    ],
    "Links": [
      {
        "Content": "[Source]",
        "Href": "https://starwars.fandom.com/wiki/Template:RPG_adventure"
      }
    ]
  }
}