{
  "PageId": 154129,
  "PageTitle": "Swift (freighter)",
  "PageUrl": "https://starwars.fandom.com/wiki/Swift_(freighter)",
  "Template": "/wiki/Template:Individual_ship",
  "Data": [
    {
      "Label": "Titles",
      "Links": [],
      "Values": [
        "Swift"
      ]
    },
    {
      "Label": "Class",
      "Links": [
        {
          "Content": "Freighter",
          "Href": "/wiki/Freighter/Legends"
        }
      ],
      "Values": [
        "Freighter"
      ]
    },
    {
      "Label": "Affiliation",
      "Links": [
        {
          "Content": "Galactic Empire",
          "Href": "/wiki/Galactic_Empire/Legends"
        },
        {
          "Content": "Ciutric Hegemony",
          "Href": "/wiki/Ciutric_Hegemony"
        }
      ],
      "Values": [
        "Galactic Empire",
        "Ciutric Hegemony"
      ]
    },
    {
      "Label": "Commander(s)",
      "Links": [
        {
          "Content": "Captain",
          "Href": "/wiki/Captain/Legends"
        },
        {
          "Content": "Wintle",
          "Href": "/wiki/Wintle"
        }
      ],
      "Values": [
        "Captain Wintle"
      ]
    }
  ],
  "Relationships": []
}