{
  "PageId": 131609,
  "PageTitle": "Empire (Imperial II prototype)",
  "PageUrl": "https://starwars.fandom.com/wiki/Empire+(Imperial+II+prototype)",
  "Titles": {
    "Values": [
      "Empire"
    ],
    "Links": []
  },
  "Template": {
    "Values": [
      "[Source]"
    ],
    "Links": [
      {
        "Content": "[Source]",
        "Href": "/wiki/Template:Individual_ship"
      }
    ]
  },
  "Model": {
    "Values": [
      "Imperial II-class Star Destroyer"
    ],
    "Links": [
      {
        "Content": "Imperial II-class Star Destroyer",
        "Href": "/wiki/Imperial_II-class_Star_Destroyer/Legends"
      }
    ]
  },
  "Modified systems": {
    "Values": [
      "Superior shielding to other ships in its class"
    ],
    "Links": []
  },
  "Role(s)": {
    "Values": [
      "Destroyer",
      "Battleship (downscaled)"
    ],
    "Links": [
      {
        "Content": "Destroyer",
        "Href": "/wiki/Destroyer/Legends"
      },
      {
        "Content": "Battleship",
        "Href": "/wiki/Battleship/Legends"
      }
    ]
  },
  "Affiliation": {
    "Values": [
      "Galactic Empire"
    ],
    "Links": [
      {
        "Content": "Galactic Empire",
        "Href": "/wiki/Galactic_Empire/Legends"
      }
    ]
  },
  "Commander(s)": {
    "Values": [
      "Admiral Feyet Kiez"
    ],
    "Links": [
      {
        "Content": "Admiral",
        "Href": "/wiki/Admiral/Legends"
      },
      {
        "Content": "Feyet Kiez",
        "Href": "/wiki/Feyet_Kiez"
      }
    ]
  }
}