{
  "PageId": 13377,
  "PageUrl": "https://starwars.fandom.com/wiki/Kemplex_Nine",
  "TemplateUrl": "https://starwars.fandom.com/wiki/Template:Space_station",
  "ImageUrl": "https://static.wikia.nocookie.net/starwars/images/8/8f/Kemplex.jpg/revision/latest?cb=20081205052436",
  "Data": [
    {
      "Label": "Titles",
      "Links": [],
      "Values": [
        "Kemplex Nine"
      ]
    },
    {
      "Label": "Type",
      "Links": [],
      "Values": [
        "jump-station"
      ]
    },
    {
      "Label": "Region",
      "Links": [
        {
          "Content": "Outer Rim Territories",
          "Href": "https://starwars.fandom.com/wiki/Outer_Rim_Territories/Legends"
        },
        {
          "Content": "Sith Space",
          "Href": "https://starwars.fandom.com/wiki/Sith_Worlds"
        }
      ],
      "Values": [
        "Outer Rim Territories",
        "Sith Space"
      ]
    },
    {
      "Label": "Sector",
      "Links": [
        {
          "Content": "Auril sector",
          "Href": "https://starwars.fandom.com/wiki/Auril_sector"
        }
      ],
      "Values": [
        "Auril sector"
      ]
    },
    {
      "Label": "System",
      "Links": [
        {
          "Content": "Cron system",
          "Href": "https://starwars.fandom.com/wiki/Cron_system"
        }
      ],
      "Values": [
        "Cron system"
      ]
    },
    {
      "Label": "Planet",
      "Links": [],
      "Values": [
        "unidentified celestial object"
      ]
    },
    {
      "Label": "Grid square",
      "Links": [],
      "Values": [
        "R-6"
      ]
    },
    {
      "Label": "Affiliation",
      "Links": [
        {
          "Content": "Galactic Republic",
          "Href": "https://starwars.fandom.com/wiki/Galactic_Republic/Legends"
        }
      ],
      "Values": [
        "Galactic Republic"
      ]
    },
    {
      "Label": "Destroyed",
      "Links": [
        {
          "Content": "3996 BBY",
          "Href": "https://starwars.fandom.com/wiki/3996_BBY"
        }
      ],
      "Values": [
        "3996 BBY"
      ]
    },
    {
      "Label": "Present for battles/events",
      "Links": [
        {
          "Content": "Battle of Kemplex Nine",
          "Href": "https://starwars.fandom.com/wiki/Battle_of_Kemplex_Nine"
        }
      ],
      "Values": [
        "Battle of Kemplex Nine"
      ]
    }
  ],
  "Relationships": [
    {
      "PageId": 18759,
      "PageUrl": "https://starwars.fandom.com/wiki/Cron_system",
      "TemplateUrl": "https://starwars.fandom.com/wiki/Template:System"
    },
    {
      "PageId": 12881,
      "PageUrl": "https://starwars.fandom.com/wiki/Cron_Cluster/Legends",
      "TemplateUrl": "https://starwars.fandom.com/wiki/Template:Star"
    },
    {
      "PageId": 27230,
      "PageUrl": "https://starwars.fandom.com/wiki/Battle_of_Kemplex_Nine",
      "TemplateUrl": "https://starwars.fandom.com/wiki/Template:Battle"
    }
  ]
}