{
  "PageId": 714771,
  "PageUrl": "https://starwars.fandom.com/wiki/Cantonarive_crown_coin",
  "TemplateUrl": "https://starwars.fandom.com/wiki/Template:Artifact",
  "ImageUrl": "https://static.wikia.nocookie.net/starwars/images/8/8c/CantonariveCrownCoin-SWAA21.jpg/revision/latest?cb=20211125035044",
  "Data": [
    {
      "Label": "Titles",
      "Links": [],
      "Values": [
        "Cantonarive crown coin"
      ]
    },
    {
      "Label": "Type",
      "Links": [
        {
          "Content": "Coin",
          "Href": "https://starwars.fandom.com/wiki/Coin"
        }
      ],
      "Values": [
        "Coin"
      ]
    },
    {
      "Label": "Place of origin",
      "Links": [
        {
          "Content": "Canto Bight",
          "Href": "https://starwars.fandom.com/wiki/Canto_Bight"
        }
      ],
      "Values": [
        "Canto Bight"
      ]
    },
    {
      "Label": "Locations",
      "Links": [
        {
          "Content": "Cloud City",
          "Href": "https://starwars.fandom.com/wiki/Cloud_City"
        },
        {
          "Content": "Bespin",
          "Href": "https://starwars.fandom.com/wiki/Bespin"
        }
      ],
      "Values": [
        "Cloud City, Bespin"
      ]
    },
    {
      "Label": "Shape",
      "Links": [],
      "Values": [
        "Round"
      ]
    },
    {
      "Label": "Color",
      "Links": [
        {
          "Content": "Gold",
          "Href": "https://starwars.fandom.com/wiki/Color"
        }
      ],
      "Values": [
        "Gold, white, and black"
      ]
    }
  ],
  "Relationships": []
}