{
  "PageId": 313735,
  "PageUrl": "https://starwars.fandom.com/wiki/Corellia_(starship)",
  "TemplateUrl": "https://starwars.fandom.com/wiki/Template:Individual_ship",
  "Data": [
    {
      "Label": "Titles",
      "Links": [],
      "Values": [
        "Corellia"
      ]
    },
    {
      "Label": "Class",
      "Links": [
        {
          "Content": "Valor-class cruiser",
          "Href": "https://starwars.fandom.com/wiki/Valor-class_cruiser"
        }
      ],
      "Values": [
        "Valor-class cruiser"
      ]
    },
    {
      "Label": "Armament",
      "Links": [
        {
          "Content": "Turbolasers",
          "Href": "https://starwars.fandom.com/wiki/Turbolaser/Legends"
        },
        {
          "Content": "Ion cannons",
          "Href": "https://starwars.fandom.com/wiki/Ion_cannon/Legends"
        },
        {
          "Content": "Ion Torpedo Launchers",
          "Href": "https://starwars.fandom.com/wiki/Ion_torpedo/Legends"
        }
      ],
      "Values": [
        "Turbolasers",
        "Ion cannons",
        "Ion Torpedo Launchers"
      ]
    },
    {
      "Label": "Complement",
      "Links": [
        {
          "Content": "XA-8 starfighters",
          "Href": "https://starwars.fandom.com/wiki/XA-8_starfighter"
        },
        {
          "Content": "PT-7 Raven-class starfighters",
          "Href": "https://starwars.fandom.com/wiki/PT-7_starfighter"
        }
      ],
      "Values": [
        "XA-8 starfighters",
        "PT-7 Raven-class starfighters"
      ]
    },
    {
      "Label": "Escape craft",
      "Links": [],
      "Values": [
        "Several escape pods"
      ]
    },
    {
      "Label": "Destroyed",
      "Links": [
        {
          "Content": "3643 BBY",
          "Href": "https://starwars.fandom.com/wiki/3643_BBY"
        }
      ],
      "Values": [
        "c. 3643 BBY"
      ]
    },
    {
      "Label": "Affiliation",
      "Links": [
        {
          "Content": "Galactic Republic",
          "Href": "https://starwars.fandom.com/wiki/Galactic_Republic/Legends"
        }
      ],
      "Values": [
        "Galactic Republic"
      ]
    },
    {
      "Label": "Commander(s)",
      "Links": [
        {
          "Content": "Grand Master",
          "Href": "https://starwars.fandom.com/wiki/Grand_Master/Legends"
        },
        {
          "Content": "Satele Shan",
          "Href": "https://starwars.fandom.com/wiki/Satele_Shan"
        },
        {
          "Content": "Colonel",
          "Href": "https://starwars.fandom.com/wiki/Colonel/Legends"
        },
        {
          "Content": "Gurin",
          "Href": "https://starwars.fandom.com/wiki/Gurin"
        }
      ],
      "Values": [
        "Grand Master Satele Shan",
        "Colonel Gurin"
      ]
    }
  ],
  "Relationships": []
}