{
  "PageId": 709189,
  "PageUrl": "https://starwars.fandom.com/wiki/Eldritch",
  "TemplateUrl": "https://starwars.fandom.com/wiki/Template:Individual_ship",
  "Data": [
    {
      "Label": "Titles",
      "Links": [],
      "Values": [
        "Eldritch"
      ]
    },
    {
      "Label": "Class",
      "Links": [
        {
          "Content": "Submersible",
          "Href": "https://starwars.fandom.com/wiki/Submersible"
        },
        {
          "Content": "starship",
          "Href": "https://starwars.fandom.com/wiki/Starship/Legends"
        }
      ],
      "Values": [
        "Submersible starship"
      ]
    },
    {
      "Label": "Affiliation",
      "Links": [
        {
          "Content": "Corellian Security Forces",
          "Href": "https://starwars.fandom.com/wiki/Corellian_Security_Forces"
        }
      ],
      "Values": [
        "Corellian Security Forces"
      ]
    }
  ],
  "Relationships": []
}