{
  "PageId": 143895,
  "PageUrl": "https://starwars.fandom.com/wiki/Great_Sea_(Kalarba)",
  "TemplateUrl": "https://starwars.fandom.com/wiki/Template:Location",
  "ImageUrl": "https://static.wikia.nocookie.net/starwars/images/c/c0/GreatSeaKalarba-TEGtPaM.png/revision/latest?cb=20070804123208",
  "Data": [
    {
      "Label": "Titles",
      "Links": [],
      "Values": [
        "Great Sea"
      ]
    },
    {
      "Label": "Location",
      "Links": [
        {
          "Content": "Kalarba",
          "Href": "https://starwars.fandom.com/wiki/Kalarba/Legends"
        }
      ],
      "Values": [
        "Kalarba"
      ]
    },
    {
      "Label": "Terrain",
      "Links": [
        {
          "Content": "Water",
          "Href": "https://starwars.fandom.com/wiki/Ocean/Legends"
        }
      ],
      "Values": [
        "Water"
      ]
    }
  ],
  "Relationships": [
    {
      "PageId": 13713,
      "PageUrl": "https://starwars.fandom.com/wiki/Kalarba/Legends",
      "TemplateUrl": "https://starwars.fandom.com/wiki/Template:Planet"
    }
  ]
}