{
  "PageId": 305325,
  "PageUrl": "https://starwars.fandom.com/wiki/Saki_Prime",
  "TemplateUrl": "https://starwars.fandom.com/wiki/Template:Star",
  "ImageUrl": null,
  "Data": [
    {
      "Label": "Titles",
      "Links": [],
      "Values": [
        "Saki Prime"
      ]
    },
    {
      "Label": "Region(s)",
      "Links": [
        {
          "Content": "Hutt Space",
          "Href": "https://starwars.fandom.com/wiki/Hutt_Space/Legends"
        },
        {
          "Content": "Bootana Hutta",
          "Href": "https://starwars.fandom.com/wiki/Bootana_Hutta"
        }
      ],
      "Values": [
        "Hutt Space",
        "Bootana Hutta"
      ]
    },
    {
      "Label": "System",
      "Links": [
        {
          "Content": "Saki system",
          "Href": "https://starwars.fandom.com/wiki/Saki_system"
        }
      ],
      "Values": [
        "Saki system"
      ]
    },
    {
      "Label": "Grid square",
      "Links": [],
      "Values": [
        "S-11"
      ]
    },
    {
      "Label": "Orbits",
      "Links": [
        {
          "Content": "Sakiya",
          "Href": "https://starwars.fandom.com/wiki/Sakiya"
        },
        {
          "Content": "moon",
          "Href": "https://starwars.fandom.com/wiki/Moon/Legends"
        }
      ],
      "Values": [
        "Sakiya",
        "1 large moon"
      ]
    },
    {
      "Label": "Class",
      "Links": [
        {
          "Content": "Red giant",
          "Href": "https://starwars.fandom.com/wiki/Red_giant/Legends"
        }
      ],
      "Values": [
        "Red giant"
      ]
    }
  ],
  "Relationships": [
    {
      "PageId": 13684,
      "PageUrl": "https://starwars.fandom.com/wiki/Sakiya",
      "TemplateUrl": "https://starwars.fandom.com/wiki/Template:Planet"
    },
    {
      "PageId": 287826,
      "PageUrl": "https://starwars.fandom.com/wiki/Saki_system",
      "TemplateUrl": "https://starwars.fandom.com/wiki/Template:System"
    }
  ]
}