{
  "PageId": 372362,
  "PageUrl": "https://starwars.fandom.com/wiki/Sarkhai_(species)",
  "TemplateUrl": "https://starwars.fandom.com/wiki/Template:Species",
  "ImageUrl": "https://static.wikia.nocookie.net/starwars/images/f/f1/Nadia_Grell.png/revision/latest?cb=20150201044205",
  "Data": [
    {
      "Label": "Titles",
      "Links": [],
      "Values": [
        "Sarkhai"
      ]
    },
    {
      "Label": "Designation",
      "Links": [
        {
          "Content": "Sentient",
          "Href": "https://starwars.fandom.com/wiki/Sentience/Legends"
        }
      ],
      "Values": [
        "Sentient"
      ]
    },
    {
      "Label": "Skin color",
      "Links": [],
      "Values": [
        "Pale"
      ]
    },
    {
      "Label": "Hair color",
      "Links": [],
      "Values": [
        "White"
      ]
    },
    {
      "Label": "Eye color",
      "Links": [],
      "Values": [
        "Blue"
      ]
    },
    {
      "Label": "Distinctions",
      "Links": [],
      "Values": [
        "White painted face with blue pattern"
      ]
    },
    {
      "Label": "Homeworld",
      "Links": [
        {
          "Content": "Sarkhai",
          "Href": "https://starwars.fandom.com/wiki/Sarkhai"
        }
      ],
      "Values": [
        "Sarkhai"
      ]
    }
  ],
  "Relationships": [
    {
      "PageId": 401509,
      "PageUrl": "https://starwars.fandom.com/wiki/Nyscha",
      "TemplateUrl": "https://starwars.fandom.com/wiki/Template:Character"
    },
    {
      "PageId": 401511,
      "PageUrl": "https://starwars.fandom.com/wiki/Sethun",
      "TemplateUrl": "https://starwars.fandom.com/wiki/Template:Character"
    },
    {
      "PageId": 401512,
      "PageUrl": "https://starwars.fandom.com/wiki/Maykia_Grell",
      "TemplateUrl": "https://starwars.fandom.com/wiki/Template:Character"
    },
    {
      "PageId": 594203,
      "PageUrl": "https://starwars.fandom.com/wiki/Tobas_Grell's_wife",
      "TemplateUrl": "https://starwars.fandom.com/wiki/Template:Character"
    },
    {
      "PageId": 547374,
      "PageUrl": "https://starwars.fandom.com/wiki/Nadia_Grell's_cousin",
      "TemplateUrl": "https://starwars.fandom.com/wiki/Template:Character"
    },
    {
      "PageId": 414744,
      "PageUrl": "https://starwars.fandom.com/wiki/Sarkhai_royal_family",
      "TemplateUrl": "https://starwars.fandom.com/wiki/Template:Family"
    },
    {
      "PageId": 363837,
      "PageUrl": "https://starwars.fandom.com/wiki/Tobas_Grell",
      "TemplateUrl": "https://starwars.fandom.com/wiki/Template:Character"
    },
    {
      "PageId": 368069,
      "PageUrl": "https://starwars.fandom.com/wiki/Sarkhai",
      "TemplateUrl": "https://starwars.fandom.com/wiki/Template:Planet"
    },
    {
      "PageId": 354237,
      "PageUrl": "https://starwars.fandom.com/wiki/Nadia_Grell",
      "TemplateUrl": "https://starwars.fandom.com/wiki/Template:Character"
    }
  ]
}