{
  "PageId": 37607,
  "PageUrl": "https://starwars.fandom.com/wiki/Kyren",
  "TemplateUrl": "https://starwars.fandom.com/wiki/Template:Species",
  "ImageUrl": null,
  "Data": [
    {
      "Label": "Titles",
      "Links": [],
      "Values": [
        "Kyren"
      ]
    },
    {
      "Label": "Classification",
      "Links": [
        {
          "Content": "Bird",
          "Href": "https://starwars.fandom.com/wiki/Bird/Legends"
        }
      ],
      "Values": [
        "Bird"
      ]
    },
    {
      "Label": "Skin color",
      "Links": [
        {
          "Content": "Jet black",
          "Href": "https://starwars.fandom.com/wiki/Color/Legends"
        }
      ],
      "Values": [
        "Jet black"
      ]
    },
    {
      "Label": "Distinctions",
      "Links": [],
      "Values": [
        "Four wings",
        "Legless"
      ]
    },
    {
      "Label": "Homeworld",
      "Links": [
        {
          "Content": "Ansion",
          "Href": "https://starwars.fandom.com/wiki/Ansion/Legends"
        }
      ],
      "Values": [
        "Ansion"
      ]
    },
    {
      "Label": "Diet",
      "Links": [
        {
          "Content": "Herbivorous",
          "Href": "https://starwars.fandom.com/wiki/Diet/Legends"
        }
      ],
      "Values": [
        "Herbivorous"
      ]
    }
  ],
  "Relationships": [
    {
      "PageId": 4193,
      "PageUrl": "https://starwars.fandom.com/wiki/Ansion/Legends",
      "TemplateUrl": "https://starwars.fandom.com/wiki/Template:Planet"
    }
  ]
}