{
  "PageId": 440454,
  "PageUrl": "https://starwars.fandom.com/wiki/Pterathki",
  "TemplateUrl": "https://starwars.fandom.com/wiki/Template:Species",
  "ImageUrl": "https://static.wikia.nocookie.net/starwars/images/5/56/Pterathki.png/revision/latest?cb=20150810131532",
  "Data": [
    {
      "Label": "Titles",
      "Links": [],
      "Values": [
        "Pterathki"
      ]
    },
    {
      "Label": "Classification",
      "Links": [
        {
          "Content": "Non-sentient",
          "Href": "https://starwars.fandom.com/wiki/Sentience/Legends"
        }
      ],
      "Values": [
        "Non-sentient"
      ]
    },
    {
      "Label": "Eye color",
      "Links": [],
      "Values": [
        "Red"
      ]
    },
    {
      "Label": "Homeworld",
      "Links": [
        {
          "Content": "Makeb",
          "Href": "https://starwars.fandom.com/wiki/Makeb"
        },
        {
          "Content": "Onderon",
          "Href": "https://starwars.fandom.com/wiki/Onderon"
        }
      ],
      "Values": [
        "Makeb",
        "Onderon"
      ]
    }
  ],
  "Relationships": [
    {
      "PageId": 417,
      "PageUrl": "https://starwars.fandom.com/wiki/Onderon/Legends",
      "TemplateUrl": "https://starwars.fandom.com/wiki/Template:Planet"
    },
    {
      "PageId": 443801,
      "PageUrl": "https://starwars.fandom.com/wiki/Dantooine_cane_syrup",
      "TemplateUrl": "https://starwars.fandom.com/wiki/Template:Food"
    },
    {
      "PageId": 381699,
      "PageUrl": "https://starwars.fandom.com/wiki/Makeb",
      "TemplateUrl": "https://starwars.fandom.com/wiki/Template:Planet"
    }
  ]
}