{
  "PageId": 627955,
  "PageUrl": "https://starwars.fandom.com/wiki/Tunda_Ress",
  "TemplateUrl": "https://starwars.fandom.com/wiki/Template:Character",
  "ImageUrl": "https://static.wikia.nocookie.net/starwars/images/e/e5/Tunda_Ress.png/revision/latest?cb=20230405155757",
  "Data": [
    {
      "Label": "Titles",
      "Links": [],
      "Values": [
        "Tunda Ress"
      ]
    },
    {
      "Label": "Species",
      "Links": [
        {
          "Content": "Humanoid",
          "Href": "https://starwars.fandom.com/wiki/Humanoid"
        }
      ],
      "Values": [
        "Humanoid"
      ]
    }
  ],
  "Relationships": []
}