{
  "PageId": 497490,
  "PageTitle": "Skirmish on the Star of Empire",
  "PageUrl": "https://starwars.fandom.com/wiki/Skirmish_on_the_Star_of_Empire",
  "Template": "https://starwars.fandom.com/wiki/Template:Battle",
  "Image": null,
  "Data": [
    {
      "Label": "Titles",
      "Links": [],
      "Values": [
        "Skirmish on the Star of Empire"
      ]
    },
    {
      "Label": "Conflict",
      "Links": [
        {
          "Content": "Galactic Civil War",
          "Href": "/wiki/Galactic_Civil_War/Legends"
        }
      ],
      "Values": [
        "Galactic Civil War"
      ]
    },
    {
      "Label": "Date",
      "Links": [
        {
          "Content": "1 BBY",
          "Href": "/wiki/1_BBY/Legends"
        }
      ],
      "Values": [
        "1 BBY"
      ]
    },
    {
      "Label": "Place",
      "Links": [
        {
          "Content": "Star of Empire",
          "Href": "/wiki/Star_of_Empire"
        }
      ],
      "Values": [
        "Star of Empire"
      ]
    },
    {
      "Label": "Outcome",
      "Links": [
        {
          "Content": "Rebel Alliance",
          "Href": "/wiki/Alliance_to_Restore_the_Republic/Legends"
        },
        {
          "Content": "Galactic Empire",
          "Href": "/wiki/Galactic_Empire/Legends"
        }
      ],
      "Values": [
        "Rebel Alliance agents escape Galactic Empire forces"
      ]
    }
  ],
  "Relationships": [
    {
      "PageId": 33254,
      "PageTitle": "Truly Sorry",
      "PageUrl": "https://starwars.fandom.com/wiki/Truly_Sorry",
      "Template": "/wiki/Template:Individual_ship"
    }
  ]
}