{
  "PageId": 703781,
  "PageTitle": "Constabulary",
  "PageUrl": "https://starwars.fandom.com/wiki/Constabulary",
  "Titles": {
    "Values": [
      "Constabulary"
    ],
    "Links": []
  },
  "Template": {
    "Values": [
      "[Source]"
    ],
    "Links": [
      {
        "Content": "[Source]",
        "Href": "https://starwars.fandom.com/wiki/Template:Structure"
      }
    ]
  },
  "Location": {
    "Values": [
      "Tasariq City, Tasariq"
    ],
    "Links": [
      {
        "Content": "Tasariq City",
        "Href": "/wiki/Tasariq_City"
      },
      {
        "Content": "Tasariq",
        "Href": "/wiki/Tasariq"
      }
    ]
  }
}