{
  "PageId": 167291,
  "PageTitle": "Aquilaean system",
  "PageUrl": "https://starwars.fandom.com/wiki/Aquilaean_system",
  "Template": "https://starwars.fandom.com/wiki/Template:System",
  "Image": null,
  "Data": [
    {
      "Label": "Titles",
      "Links": [],
      "Values": [
        "Aquilaean system"
      ]
    },
    {
      "Label": "Orbits",
      "Links": [
        {
          "Content": "Aquilae",
          "Href": "/wiki/Aquilae_(The_Star_Wars)"
        }
      ],
      "Values": [
        "Aquilae"
      ]
    }
  ],
  "Relationships": [
    {
      "PageId": 429050,
      "PageTitle": "Aquilae (The Star Wars)",
      "PageUrl": "https://starwars.fandom.com/wiki/Aquilae_(The_Star_Wars)",
      "Template": "https://starwars.fandom.com/wiki/Template:Planet"
    }
  ]
}