{
  "PageId": 361399,
  "PageTitle": "Lamus system",
  "PageUrl": "https://starwars.fandom.com/wiki/Lamus_system",
  "Template": "https://starwars.fandom.com/wiki/Template:System",
  "Image": null,
  "Data": [
    {
      "Label": "Titles",
      "Links": [],
      "Values": [
        "Lamus system"
      ]
    },
    {
      "Label": "Region",
      "Links": [
        {
          "Content": "Outer Rim Territories",
          "Href": "/wiki/Outer_Rim_Territories/Legends"
        }
      ],
      "Values": [
        "Outer Rim Territories"
      ]
    },
    {
      "Label": "Sector",
      "Links": [
        {
          "Content": "Sertar sector",
          "Href": "/wiki/Sertar_sector/Legends"
        }
      ],
      "Values": [
        "Sertar sector"
      ]
    },
    {
      "Label": "Grid coordinates",
      "Links": [],
      "Values": [
        "R-5"
      ]
    },
    {
      "Label": "Orbits",
      "Links": [
        {
          "Content": "Lamus",
          "Href": "/wiki/Lamus"
        }
      ],
      "Values": [
        "Lamus"
      ]
    }
  ],
  "Relationships": [
    {
      "PageId": 14736,
      "PageTitle": "Lamus",
      "PageUrl": "https://starwars.fandom.com/wiki/Lamus",
      "Template": "https://starwars.fandom.com/wiki/Template:Planet"
    },
    {
      "PageId": 272769,
      "PageTitle": "Sertar sector/Legends",
      "PageUrl": "https://starwars.fandom.com/wiki/Sertar_sector%2fLegends",
      "Template": "https://starwars.fandom.com/wiki/Template:Sector"
    }
  ]
}