{
  "PageId": 391529,
  "PageTitle": "Kor Hunamma system",
  "PageUrl": "https://starwars.fandom.com/wiki/Kor_Hunamma_system",
  "Template": "https://starwars.fandom.com/wiki/Template:System",
  "Image": "https://static.wikia.nocookie.net/starwars/images/e/ed/BootanaHuttaCluster-TEA.png/revision/latest?cb=20171211205003",
  "Data": [
    {
      "Label": "Titles",
      "Links": [],
      "Values": [
        "Kor Hunamma system(#8 on map)"
      ]
    },
    {
      "Label": "Region",
      "Links": [
        {
          "Content": "Hutt Space",
          "Href": "/wiki/Hutt_Space/Legends"
        },
        {
          "Content": "Bootana Hutta",
          "Href": "/wiki/Bootana_Hutta"
        }
      ],
      "Values": [
        "Hutt Space",
        "Bootana Hutta"
      ]
    },
    {
      "Label": "Grid coordinates",
      "Links": [],
      "Values": [
        "S-11"
      ]
    },
    {
      "Label": "Orbits",
      "Links": [
        {
          "Content": "Kor Hunamma",
          "Href": "/wiki/Kor_Hunamma"
        }
      ],
      "Values": [
        "Kor Hunamma"
      ]
    }
  ],
  "Relationships": [
    {
      "PageId": 270287,
      "PageTitle": "Kor Hunamma",
      "PageUrl": "https://starwars.fandom.com/wiki/Kor_Hunamma",
      "Template": "https://starwars.fandom.com/wiki/Template:Planet"
    },
    {
      "PageId": 2528,
      "PageTitle": "Hutt Space/Legends",
      "PageUrl": "https://starwars.fandom.com/wiki/Hutt_Space%2fLegends",
      "Template": "https://starwars.fandom.com/wiki/Template:Sector"
    },
    {
      "PageId": 270273,
      "PageTitle": "Bootana Hutta",
      "PageUrl": "https://starwars.fandom.com/wiki/Bootana_Hutta",
      "Template": "https://starwars.fandom.com/wiki/Template:Sector"
    }
  ]
}