{
  "PageId": 257659,
  "PageTitle": "F-RTZ-2",
  "PageUrl": "https://starwars.fandom.com/wiki/F-RTZ-2",
  "Template": "https://starwars.fandom.com/wiki/Template:Droid_series",
  "Data": [
    {
      "Label": "Titles",
      "Links": [],
      "Values": [
        "F-RTZ-2"
      ]
    },
    {
      "Label": "Equipment",
      "Links": [
        {
          "Content": "Holorecording",
          "Href": "/wiki/Holorecording"
        },
        {
          "Content": "Repulsorlift",
          "Href": "/wiki/Repulsorlift/Legends"
        }
      ],
      "Values": [
        "Holorecording unit",
        "Repulsorlift unit"
      ]
    },
    {
      "Label": "Affiliation",
      "Links": [
        {
          "Content": "MD-0C6",
          "Href": "/wiki/MD-0C6"
        }
      ],
      "Values": [
        "MD-0C6"
      ]
    }
  ],
  "Relationships": []
}