{
  "PageId": 54248,
  "PageTitle": "Kolkpravis",
  "PageUrl": "https://starwars.fandom.com/wiki/Kolkpravis",
  "Template": "https://starwars.fandom.com/wiki/Template:Government",
  "Image": "https://static.wikia.nocookie.net/starwars/images/3/31/KaleeshKolkpravisWarriors-GAW.jpg/revision/latest?cb=20091029124854",
  "Data": [
    {
      "Label": "Titles",
      "Links": [],
      "Values": [
        "Kolkpravis"
      ]
    },
    {
      "Label": "Organization type",
      "Links": [],
      "Values": [
        "Khanate"
      ]
    },
    {
      "Label": "Head of state",
      "Links": [
        {
          "Content": "Khagan",
          "Href": "/wiki/Khagan"
        }
      ],
      "Values": [
        "Khagan"
      ]
    },
    {
      "Label": "Head of government",
      "Links": [],
      "Values": [
        "Khagan"
      ]
    },
    {
      "Label": "Commander-in-chief",
      "Links": [],
      "Values": [
        "Khagan"
      ]
    },
    {
      "Label": "De facto\u00A0leader",
      "Links": [
        {
          "Content": "Bentilais san Sk'ar",
          "Href": "/wiki/Bentilais_san_Sk%27ar"
        },
        {
          "Content": "Unknown female Kaleesh",
          "Href": "/wiki/Unidentified_female_Kaleesh_leader"
        }
      ],
      "Values": [
        "Bentilais san Sk'ar",
        "Unknown female Kaleesh"
      ]
    },
    {
      "Label": "Military branch",
      "Links": [
        {
          "Content": "Izvoshra",
          "Href": "/wiki/Izvoshra"
        }
      ],
      "Values": [
        "Izvoshra"
      ]
    },
    {
      "Label": "Capital",
      "Links": [
        {
          "Content": "Kalee",
          "Href": "/wiki/Kalee/Legends"
        }
      ],
      "Values": [
        "Kalee"
      ]
    },
    {
      "Label": "Date established",
      "Links": [
        {
          "Content": "42 BBY",
          "Href": "/wiki/42_BBY/Legends"
        }
      ],
      "Values": [
        "Before 42 BBY"
      ]
    }
  ],
  "Relationships": [
    {
      "PageId": 28375,
      "PageTitle": "Bentilais san Sk'ar",
      "PageUrl": "https://starwars.fandom.com/wiki/Bentilais_san_Sk%27ar",
      "Template": "https://starwars.fandom.com/wiki/Template:Character"
    },
    {
      "PageId": 348,
      "PageTitle": "Grievous/Legends",
      "PageUrl": "https://starwars.fandom.com/wiki/Grievous%2fLegends",
      "Template": "https://starwars.fandom.com/wiki/Template:Character"
    },
    {
      "PageId": 4877,
      "PageTitle": "Kalee/Legends",
      "PageUrl": "https://starwars.fandom.com/wiki/Kalee%2fLegends",
      "Template": "https://starwars.fandom.com/wiki/Template:Planet"
    }
  ]
}