{
  "PageId": 1079,
  "PageTitle": "Hapes Consortium/Legends",
  "Image": "https://static.wikia.nocookie.net/starwars/images/0/05/Hapes_Consortium.svg/revision/latest?cb=20080311185451",
  "Titles": {
    "Values": [
      "Hapes Consortium"
    ],
    "Links": []
  },
  "Template": {
    "Values": [
      "[Source]"
    ],
    "Links": [
      {
        "Content": "[Source]",
        "Href": "https://starwars.fandom.com/wiki/Template:Government"
      }
    ]
  },
  "Organization type": {
    "Values": [
      "Constitutional monarchy"
    ],
    "Links": [
      {
        "Content": "monarchy",
        "Href": "/wiki/Monarchy/Legends"
      }
    ]
  },
  "Head of state": {
    "Values": [
      "Queen Mother"
    ],
    "Links": [
      {
        "Content": "Queen Mother",
        "Href": "/wiki/Queen_Mother"
      }
    ]
  },
  "Head of government": {
    "Values": [
      "Queen Mother"
    ],
    "Links": []
  },
  "Commander-in-chief": {
    "Values": [
      "Royal High Commander"
    ],
    "Links": [
      {
        "Content": "Royal High Commander",
        "Href": "/wiki/Royal_High_Commander"
      }
    ]
  },
  "Legislative branch": {
    "Values": [
      "Hapan Royal Court"
    ],
    "Links": [
      {
        "Content": "Hapan Royal Court",
        "Href": "/wiki/Hapan_Royal_Court"
      }
    ]
  },
  "Military branch": {
    "Values": [
      "Hapan Royal Navy"
    ],
    "Links": [
      {
        "Content": "Hapan Royal Navy",
        "Href": "/wiki/Hapan_Royal_Navy"
      }
    ]
  },
  "Capital": {
    "Values": [
      "Hapes"
    ],
    "Links": [
      {
        "Content": "Hapes",
        "Href": "/wiki/Hapes/Legends"
      }
    ]
  },
  "Official language": {
    "Values": [
      "Hapan"
    ],
    "Links": [
      {
        "Content": "Hapan",
        "Href": "/wiki/Hapan_(language)"
      }
    ]
  },
  "Currency": {
    "Values": [
      "Galactic Credit Standard"
    ],
    "Links": [
      {
        "Content": "Galactic Credit Standard",
        "Href": "/wiki/Galactic_Credit_Standard"
      }
    ]
  },
  "Formed from": {
    "Values": [
      "Lorell Raiders"
    ],
    "Links": [
      {
        "Content": "Lorell Raiders",
        "Href": "/wiki/Lorell_Raiders"
      }
    ]
  },
  "Date established": {
    "Values": [
      "c. 4050 BBY"
    ],
    "Links": [
      {
        "Content": "4050 BBY",
        "Href": "/wiki/4050_BBY"
      }
    ]
  },
  "Date restored": {
    "Values": [
      "c. 3000 BBY"
    ],
    "Links": [
      {
        "Content": "3000 BBY",
        "Href": "/wiki/3000_BBY"
      }
    ]
  }
}