{
  "PageId": 210052,
  "PageTitle": "Unidentified Kitonak Jedi",
  "PageUrl": "https://starwars.fandom.com/wiki/Unidentified_Kitonak_Jedi",
  "Template": "https://starwars.fandom.com/wiki/Template:Character",
  "Data": [
    {
      "Label": "Titles",
      "Links": [],
      "Values": [
        "Kitonak Jedi"
      ]
    },
    {
      "Label": "Species",
      "Links": [
        {
          "Content": "Kitonak",
          "Href": "/wiki/Kitonak/Legends"
        }
      ],
      "Values": [
        "Kitonak"
      ]
    },
    {
      "Label": "Gender",
      "Links": [
        {
          "Content": "Female",
          "Href": "/wiki/Gender/Legends"
        }
      ],
      "Values": [
        "Female"
      ]
    },
    {
      "Label": "Affiliation(s)",
      "Links": [
        {
          "Content": "New Jedi Order",
          "Href": "/wiki/New_Jedi_Order"
        },
        {
          "Content": "Galactic Federation of Free Alliances",
          "Href": "/wiki/Galactic_Federation_of_Free_Alliances"
        }
      ],
      "Values": [
        "New Jedi Order",
        "Galactic Federation of Free Alliances"
      ]
    }
  ],
  "Relationships": []
}