{
  "PageId": 390806,
  "PageTitle": "Aliza Darsk",
  "PageUrl": "https://starwars.fandom.com/wiki/Aliza_Darsk",
  "Template": "https://starwars.fandom.com/wiki/Template:Character",
  "Image": "https://static.wikia.nocookie.net/starwars/images/6/6f/Aliza_Darsk.jpg/revision/latest?cb=20120902144528",
  "Data": [
    {
      "Label": "Titles",
      "Links": [],
      "Values": [
        "Aliza Darsk"
      ]
    },
    {
      "Label": "Species",
      "Links": [
        {
          "Content": "Human",
          "Href": "/wiki/Human/Legends"
        }
      ],
      "Values": [
        "Human"
      ]
    },
    {
      "Label": "Gender",
      "Links": [
        {
          "Content": "Female",
          "Href": "/wiki/Gender/Legends"
        }
      ],
      "Values": [
        "Female"
      ]
    }
  ],
  "Relationships": []
}