{
  "PageId": 44087,
  "PageTitle": "Gandroff",
  "PageUrl": "https://starwars.fandom.com/wiki/Gandroff",
  "Template": "https://starwars.fandom.com/wiki/Template:Character",
  "Image": "https://static.wikia.nocookie.net/starwars/images/1/13/Gandroff.jpg/revision/latest?cb=20090725151317",
  "Data": [
    {
      "Label": "Titles",
      "Links": [],
      "Values": [
        "Gandroff"
      ]
    },
    {
      "Label": "Homeworld",
      "Links": [
        {
          "Content": "Taris",
          "Href": "/wiki/Taris/Legends"
        }
      ],
      "Values": [
        "Taris"
      ]
    },
    {
      "Label": "Species",
      "Links": [
        {
          "Content": "Human",
          "Href": "/wiki/Human/Legends"
        }
      ],
      "Values": [
        "Human"
      ]
    },
    {
      "Label": "Gender",
      "Links": [
        {
          "Content": "Male",
          "Href": "/wiki/Gender/Legends"
        }
      ],
      "Values": [
        "Male"
      ]
    },
    {
      "Label": "Hair color",
      "Links": [
        {
          "Content": "Graying black",
          "Href": "/wiki/Color/Legends"
        }
      ],
      "Values": [
        "Graying black"
      ]
    },
    {
      "Label": "Eye color",
      "Links": [],
      "Values": [
        "Brown"
      ]
    },
    {
      "Label": "Skin color",
      "Links": [],
      "Values": [
        "Brown"
      ]
    }
  ],
  "Relationships": []
}