{
  "PageId": 498925,
  "PageTitle": "Malé-Dee",
  "PageUrl": "https://starwars.fandom.com/wiki/Mal%c3%a9-Dee",
  "Template": "https://starwars.fandom.com/wiki/Template:Character",
  "Image": "https://static.wikia.nocookie.net/starwars/images/5/55/Male-Dee_CVD.png/revision/latest?cb=20210731115834",
  "Data": [
    {
      "Label": "Titles",
      "Links": [],
      "Values": [
        "Malé-Dee"
      ]
    },
    {
      "Label": "Species",
      "Links": [
        {
          "Content": "Human",
          "Href": "/wiki/Human"
        }
      ],
      "Values": [
        "Human"
      ]
    },
    {
      "Label": "Gender",
      "Links": [
        {
          "Content": "Male",
          "Href": "/wiki/Gender"
        }
      ],
      "Values": [
        "Male"
      ]
    },
    {
      "Label": "Hair color",
      "Links": [
        {
          "Content": "Red",
          "Href": "/wiki/Color"
        }
      ],
      "Values": [
        "Red"
      ]
    },
    {
      "Label": "Eye color",
      "Links": [],
      "Values": [
        "Brown"
      ]
    },
    {
      "Label": "Skin color",
      "Links": [],
      "Values": [
        "Fair"
      ]
    },
    {
      "Label": "Affiliation(s)",
      "Links": [
        {
          "Content": "Galactic Republic",
          "Href": "/wiki/Galactic_Republic"
        },
        {
          "Content": "Delegation of 2,000",
          "Href": "/wiki/Delegation_of_2,000"
        }
      ],
      "Values": [
        "Galactic Republic",
        "Delegation of 2,000"
      ]
    }
  ],
  "Relationships": []
}