{
  "PageId": 676331,
  "PageTitle": "M'dwello Di",
  "PageUrl": "https://starwars.fandom.com/wiki/M%27dwello_Di",
  "Template": "https://starwars.fandom.com/wiki/Template:Character",
  "Image": "https://static.wikia.nocookie.net/starwars/images/b/b9/MdwelloDi.png/revision/latest?cb=20201205003831",
  "Data": [
    {
      "Label": "Titles",
      "Links": [],
      "Values": [
        "M'dwello Di"
      ]
    },
    {
      "Label": "Species",
      "Links": [
        {
          "Content": "Nikto",
          "Href": "/wiki/Nikto"
        },
        {
          "Content": "Kajain'sa'Nikto",
          "Href": "/wiki/Kajain%27sa%27Nikto"
        }
      ],
      "Values": [
        "Nikto (Kajain'sa'Nikto)"
      ]
    }
  ],
  "Relationships": []
}