{
  "PageId": 55885,
  "PageTitle": "Rial Pernon",
  "Image": "https://static.wikia.nocookie.net/starwars/images/7/76/Rial_Pernon1.jpg/revision/latest?cb=20081205163251",
  "Titles": {
    "Values": [
      "Rial Pernon"
    ],
    "Links": []
  },
  "Template": {
    "Values": [
      "[Source]"
    ],
    "Links": [
      {
        "Content": "[Source]",
        "Href": "https://starwars.fandom.com/wiki/Template:Character"
      }
    ]
  },
  "Homeworld": {
    "Values": [
      "Eiattu 6"
    ],
    "Links": [
      {
        "Content": "Eiattu 6",
        "Href": "/wiki/Eiattu_6"
      }
    ]
  },
  "Species": {
    "Values": [
      "Human"
    ],
    "Links": [
      {
        "Content": "Human",
        "Href": "/wiki/Human/Legends"
      }
    ]
  },
  "Gender": {
    "Values": [
      "Male"
    ],
    "Links": [
      {
        "Content": "Male",
        "Href": "/wiki/Gender/Legends"
      }
    ]
  },
  "Hair color": {
    "Values": [
      "Brown"
    ],
    "Links": []
  },
  "Affiliation(s)": {
    "Values": [
      "Priamsta",
      "Royal Family of Eiattu"
    ],
    "Links": [
      {
        "Content": "Priamsta",
        "Href": "/wiki/Priamsta"
      }
    ]
  }
}