{
  "PageId": 251252,
  "PageTitle": "Zym",
  "PageUrl": "https://starwars.fandom.com/wiki/Zym",
  "Image": "https://static.wikia.nocookie.net/starwars/images/5/5e/Master_Zym_infobox.jpg/revision/latest?cb=20090925175205",
  "Titles": {
    "Values": [
      "Zym"
    ],
    "Links": []
  },
  "Template": {
    "Values": [
      "[Source]"
    ],
    "Links": [
      {
        "Content": "[Source]",
        "Href": "https://starwars.fandom.com/wiki/Template:Character"
      }
    ]
  },
  "Died": {
    "Values": [
      "3653 BBY, Coruscant"
    ],
    "Links": [
      {
        "Content": "3653 BBY",
        "Href": "/wiki/3653_BBY"
      },
      {
        "Content": "Coruscant",
        "Href": "/wiki/Coruscant/Legends"
      }
    ]
  },
  "Species": {
    "Values": [
      "Kel Dor"
    ],
    "Links": [
      {
        "Content": "Kel Dor",
        "Href": "/wiki/Kel_Dor/Legends"
      }
    ]
  },
  "Gender": {
    "Values": [
      "Male"
    ],
    "Links": [
      {
        "Content": "Male",
        "Href": "/wiki/Gender/Legends"
      }
    ]
  },
  "Hair color": {
    "Values": [
      "None"
    ],
    "Links": []
  },
  "Eye color": {
    "Values": [
      "Silver"
    ],
    "Links": [
      {
        "Content": "Silver",
        "Href": "/wiki/Color/Legends"
      }
    ]
  },
  "Skin color": {
    "Values": [
      "Orange"
    ],
    "Links": []
  },
  "Affiliation(s)": {
    "Values": [
      "Jedi Order",
      "Galactic Republic"
    ],
    "Links": [
      {
        "Content": "Jedi Order",
        "Href": "/wiki/Jedi_Order/Legends"
      },
      {
        "Content": "Galactic Republic",
        "Href": "/wiki/Galactic_Republic/Legends"
      }
    ]
  },
  "_Relationships_": {
    "Mentions": [
      {
        "PageId": 266059,
        "PageTitle": "Alderaan peace conference",
        "PageUrl": "https://starwars.fandom.com/wiki/Alderaan_peace_conference",
        "Template": "Event"
      }
    ]
  }
}