{
  "PageId": 222987,
  "PageTitle": "S'hrah",
  "PageUrl": "https://starwars.fandom.com/wiki/S%27hrah",
  "Titles": {
    "Values": [
      "S'hrah"
    ],
    "Links": []
  },
  "Template": {
    "Values": [
      "[Source]"
    ],
    "Links": [
      {
        "Content": "[Source]",
        "Href": "https://starwars.fandom.com/wiki/Template:Character"
      }
    ]
  },
  "Gender": {
    "Values": [
      "Male"
    ],
    "Links": [
      {
        "Content": "Male",
        "Href": "/wiki/Gender/Legends"
      }
    ]
  }
}