{
  "PageId": 81947,
  "PageUrl": "https://starwars.fandom.com/wiki/Destabilization",
  "TemplateUrl": "https://starwars.fandom.com/wiki/Template:Organization",
  "ImageUrl": null,
  "Data": [
    {
      "Label": "Titles",
      "Links": [],
      "Values": [
        "Destabilization"
      ]
    },
    {
      "Label": "Affiliation",
      "Links": [
        {
          "Content": "Galactic Empire",
          "Href": "https://starwars.fandom.com/wiki/Galactic_Empire/Legends"
        },
        {
          "Content": "Imperial Intelligence",
          "Href": "https://starwars.fandom.com/wiki/Imperial_Intelligence/Legends"
        },
        {
          "Content": "Bureau of Operations",
          "Href": "https://starwars.fandom.com/wiki/Bureau_of_Operations/Legends"
        }
      ],
      "Values": [
        "Galactic Empire",
        "Imperial Intelligence",
        "Bureau of Operations"
      ]
    }
  ],
  "Relationships": [
    {
      "PageId": 408220,
      "PageUrl": "https://starwars.fandom.com/wiki/Vanel_(Human)",
      "TemplateUrl": "https://starwars.fandom.com/wiki/Template:Character"
    },
    {
      "PageId": 355809,
      "PageUrl": "https://starwars.fandom.com/wiki/Limeren",
      "TemplateUrl": "https://starwars.fandom.com/wiki/Template:Character"
    },
    {
      "PageId": 355811,
      "PageUrl": "https://starwars.fandom.com/wiki/Huv",
      "TemplateUrl": "https://starwars.fandom.com/wiki/Template:Character"
    },
    {
      "PageId": 355815,
      "PageUrl": "https://starwars.fandom.com/wiki/Flodon",
      "TemplateUrl": "https://starwars.fandom.com/wiki/Template:Character"
    },
    {
      "PageId": 259024,
      "PageUrl": "https://starwars.fandom.com/wiki/Generet",
      "TemplateUrl": "https://starwars.fandom.com/wiki/Template:Character"
    }
  ]
}